.installed.cfg
.mr.developer.cfg
CHANGES.rst
MANIFEST.in
README.rst
buildout.cfg
setup.py
versions.cfg
src/pyramid_lxneng/__init__.py
src/pyramid_lxneng/utils.py
src/pyramid_lxneng/view.py
src/pyramid_lxneng.egg-info/PKG-INFO
src/pyramid_lxneng.egg-info/SOURCES.txt
src/pyramid_lxneng.egg-info/dependency_links.txt
src/pyramid_lxneng.egg-info/entry_points.txt
src/pyramid_lxneng.egg-info/not-zip-safe
src/pyramid_lxneng.egg-info/requires.txt
src/pyramid_lxneng.egg-info/top_level.txt
src/pyramid_lxneng/scaffolds/__init__.py
src/pyramid_lxneng/scaffolds/lxneng_mongoengine/.gitignore
src/pyramid_lxneng/scaffolds/lxneng_mongoengine/CHANGES.rst
src/pyramid_lxneng/scaffolds/lxneng_mongoengine/MANIFEST.in_tmpl
src/pyramid_lxneng/scaffolds/lxneng_mongoengine/README.rst
src/pyramid_lxneng/scaffolds/lxneng_mongoengine/bootstrap.py
src/pyramid_lxneng/scaffolds/lxneng_mongoengine/buildout.cfg_tmpl
src/pyramid_lxneng/scaffolds/lxneng_mongoengine/development.ini_tmpl
src/pyramid_lxneng/scaffolds/lxneng_mongoengine/production.ini_tmpl
src/pyramid_lxneng/scaffolds/lxneng_mongoengine/requirements.txt
src/pyramid_lxneng/scaffolds/lxneng_mongoengine/setup.py_tmpl
src/pyramid_lxneng/scaffolds/lxneng_mongoengine/versions.cfg
src/pyramid_lxneng/scaffolds/lxneng_mongoengine/src/+package+/__init__.py_tmpl
src/pyramid_lxneng/scaffolds/lxneng_mongoengine/src/+package+/models/__init__.py
src/pyramid_lxneng/scaffolds/lxneng_mongoengine/src/+package+/static/favicon.ico
src/pyramid_lxneng/scaffolds/lxneng_mongoengine/src/+package+/static/robots.txt
src/pyramid_lxneng/scaffolds/lxneng_mongoengine/src/+package+/templates/404.html
src/pyramid_lxneng/scaffolds/lxneng_mongoengine/src/+package+/templates/home.html
src/pyramid_lxneng/scaffolds/lxneng_mongoengine/src/+package+/views/__init__.py
src/pyramid_lxneng/scaffolds/lxneng_plugin/.gitignore
src/pyramid_lxneng/scaffolds/lxneng_plugin/CHANGES.rst_tmpl
src/pyramid_lxneng/scaffolds/lxneng_plugin/README.rst
src/pyramid_lxneng/scaffolds/lxneng_plugin/bootstrap.py
src/pyramid_lxneng/scaffolds/lxneng_plugin/buildout.cfg_tmpl
src/pyramid_lxneng/scaffolds/lxneng_plugin/setup.py_tmpl
src/pyramid_lxneng/scaffolds/lxneng_plugin/src/+package+/__init__.py_tmpl
src/pyramid_lxneng/scaffolds/lxneng_sqlalchemy/.gitignore
