Metadata-Version: 1.0
Name: pyramid-lxneng
Version: 1.3.1
Summary: pyramid_lxneng pyramid scaffold
Home-page: https://github.com/lxneng/pyramid_lxneng
Author: Eric Lo
Author-email: lxneng@gmail.com
License: UNKNOWN
Platform: UNKNOWN
